eztransformer/.env.example
eztransformer/__init__.py
eztransformer/__main__.py
eztransformer/gpt.py
eztransformer/gpt_utils.py
eztransformer-0.1.2.dist-info/LICENSE
eztransformer-0.1.2.dist-info/METADATA
eztransformer-0.1.2.dist-info/WHEEL
eztransformer-0.1.2.dist-info/entry_points.txt
eztransformer-0.1.2.dist-info/RECORD
