Metadata-Version: 2.1
Name: eztransformer
Version: 0.1.2
Summary: faster, simpler, more interpretable nanoGPT
Home-page: https://github.com/ezhang7423/eztransformer
License: MIT
Author: ezhang7423
Author-email: ete@ucsb.edu
Requires-Python: >=3.6,<4.0
Classifier: Development Status :: 3 - Alpha
Classifier: Intended Audience :: Developers
Classifier: License :: OSI Approved :: MIT License
Classifier: Operating System :: OS Independent
Classifier: Programming Language :: Python :: 3
Classifier: Programming Language :: Python :: 3.6
Classifier: Programming Language :: Python :: 3.7
Classifier: Programming Language :: Python :: 3.8
Classifier: Programming Language :: Python :: 3.9
Classifier: Programming Language :: Python :: 3.10
Classifier: Programming Language :: Python :: 3.11
Classifier: Topic :: Software Development :: Libraries :: Python Modules
Requires-Dist: eztils (>=0.4.75,<0.5.0)
Requires-Dist: loguru (>=0.7.0,<0.8.0)
Requires-Dist: python-dotenv (>=1.0.0,<2.0.0)
Requires-Dist: rich (>=13.4.2,<14.0.0)
Requires-Dist: torch (==2.0.0)
Requires-Dist: typer-config (>=1.2.1,<2.0.0)
Requires-Dist: typer[all] (>=0.9.0,<0.10.0)
Project-URL: Repository, https://github.com/ezhang7423/eztransformer
